wordle/__init__.py
wordle/__main__.py
wordle/words.txt
cli_wordle-0.0.1.dist-info/LICENSE
cli_wordle-0.0.1.dist-info/METADATA
cli_wordle-0.0.1.dist-info/WHEEL
cli_wordle-0.0.1.dist-info/entry_points.txt
cli_wordle-0.0.1.dist-info/top_level.txt
cli_wordle-0.0.1.dist-info/RECORD
