Metadata-Version: 2.1
Name: cli-wordle
Version: 0.0.1
Summary: Wordle in Terminal
Home-page: https://github.com/er-knight/wordle
Author: Ajay Dandge
License: MIT
Keywords: wordle,terminal
Platform: UNKNOWN
Classifier: Environment :: Console
Classifier: License :: OSI Approved :: MIT License
Classifier: Operating System :: Microsoft :: Windows
Classifier: Operating System :: MacOS
Classifier: Operating System :: POSIX :: Linux
Classifier: Programming Language :: Python :: 3
Classifier: Topic :: Games/Entertainment :: Puzzle Games
Requires-Python: >=3.7
License-File: LICENSE
Requires-Dist: colorama (==0.4.4)
Requires-Dist: commonmark (==0.9.1)
Requires-Dist: Pygments (==2.11.2)
Requires-Dist: pyperclip (==1.8.2)
Requires-Dist: rich (==10.16.2)
